pytest_aws_apigateway/__init__.py
pytest_aws_apigateway/apigateway.py
pytest_aws_apigateway/context.py
pytest_aws_apigateway/integration.py
pytest_aws_apigateway/plugin.py
pytest_aws_apigateway-0.7.1.dist-info/LICENSE
pytest_aws_apigateway-0.7.1.dist-info/METADATA
pytest_aws_apigateway-0.7.1.dist-info/WHEEL
pytest_aws_apigateway-0.7.1.dist-info/entry_points.txt
pytest_aws_apigateway-0.7.1.dist-info/top_level.txt
pytest_aws_apigateway-0.7.1.dist-info/RECORD
