Metadata-Version: 2.1
Name: pytest-aws-apigateway
Version: 0.7.1
Summary: pytest plugin for AWS ApiGateway
Author-email: Felix Scherz <felixwscherz@gmail.com>
License: MIT License
Project-URL: Documentation, https://github.com/felixscherz/pytest-aws-apigateway#readme
Project-URL: Issues, https://github.com/felixscherz/pytest-aws-apigateway/issues
Project-URL: Source, https://github.com/felixscherz/pytest-aws-apigateway
Classifier: Development Status :: 4 - Beta
Classifier: Programming Language :: Python
Classifier: Programming Language :: Python :: 3.9
Classifier: Programming Language :: Python :: 3.10
Classifier: Programming Language :: Python :: 3.11
Classifier: Programming Language :: Python :: 3.12
Classifier: Programming Language :: Python :: Implementation :: CPython
Classifier: Programming Language :: Python :: Implementation :: PyPy
Classifier: Framework :: Pytest
Requires-Python: >=3.9
License-File: LICENSE
Requires-Dist: pytest
Requires-Dist: pytest-httpx
Requires-Dist: httpx
